configlite/__init__.py
configlite/config.py
configlite-0.1.6.dist-info/licenses/LICENSE
configlite-0.1.6.dist-info/METADATA
configlite-0.1.6.dist-info/WHEEL
configlite-0.1.6.dist-info/top_level.txt
configlite-0.1.6.dist-info/RECORD
