Metadata-Version: 2.4
Name: configlite
Version: 0.1.6
Summary: Lightweight self-healing config manager
Keywords: config,configuration,yaml,defaults,self-healing,lightweight,python
Classifier: License :: OSI Approved :: MIT License
Classifier: Programming Language :: Python :: 3.10
Classifier: Programming Language :: Python :: 3.11
Classifier: Programming Language :: Python :: 3.12
Classifier: Operating System :: OS Independent
Requires-Python: >=3.10
License-File: LICENSE
Requires-Dist: pyyaml>=6.0.3
Provides-Extra: dev
Requires-Dist: bumpver>=2025.1131; extra == "dev"
Requires-Dist: pre-commit>=4.5.0; extra == "dev"
Requires-Dist: pytest>=9.0.1; extra == "dev"
Requires-Dist: pytest-cov>=7.0.0; extra == "dev"
Dynamic: license-file
